bitprim_native.cp37-win_amd64.pyd
bitprim_native-1.1.162.dist-info/METADATA
bitprim_native-1.1.162.dist-info/RECORD
bitprim_native-1.1.162.dist-info/WHEEL
bitprim_native-1.1.162.dist-info/top_level.txt
