Metadata-Version: 2.1
Name: bitprim-native
Version: 1.1.162
Summary: Bitprim Platform
Home-page: https://github.com/bitprim/bitprim-py
Author: Bitprim Inc
Author-email: dev@bitprim.org
License: MIT
Keywords: bitcoin litecoin cash money bitprim
Platform: UNKNOWN
Classifier: Development Status :: 3 - Alpha
Classifier: Intended Audience :: Developers
Classifier: Topic :: Software Development :: Build Tools
Classifier: License :: OSI Approved :: MIT License
Classifier: Programming Language :: C++
Classifier: Programming Language :: Python :: 2
Classifier: Programming Language :: Python :: 2.7
Classifier: Programming Language :: Python :: 3
Classifier: Programming Language :: Python :: 3.4
Classifier: Programming Language :: Python :: 3.5
Classifier: Programming Language :: Python :: 3.6
Provides-Extra: test
Provides-Extra: dev
